__init__.py
config.py
dbt_erd.py
mermaid_generator.py
mermaid_renderer.py
model_analyzer.py
utils.py
yaml_manager.py
dbt_model_erd-0.1.1.dist-info/licenses/LICENSE
dbt_model_erd-0.1.1.dist-info/METADATA
dbt_model_erd-0.1.1.dist-info/WHEEL
dbt_model_erd-0.1.1.dist-info/entry_points.txt
dbt_model_erd-0.1.1.dist-info/top_level.txt
dbt_model_erd-0.1.1.dist-info/RECORD
